odoo/addons/delivery_roulier_geodis_fr/README.rst
odoo/addons/delivery_roulier_geodis_fr/__init__.py
odoo/addons/delivery_roulier_geodis_fr/__manifest__.py
odoo/addons/delivery_roulier_geodis_fr/data/delivery.xml
odoo/addons/delivery_roulier_geodis_fr/data/product.xml
odoo/addons/delivery_roulier_geodis_fr/data/sequence_geodis.xml
odoo/addons/delivery_roulier_geodis_fr/i18n/delivery_roulier_geodis_fr.pot
odoo/addons/delivery_roulier_geodis_fr/i18n/it.po
odoo/addons/delivery_roulier_geodis_fr/models/__init__.py
odoo/addons/delivery_roulier_geodis_fr/models/carrier_account.py
odoo/addons/delivery_roulier_geodis_fr/models/delivery_carrier.py
odoo/addons/delivery_roulier_geodis_fr/models/delivery_carrier_agency.py
odoo/addons/delivery_roulier_geodis_fr/models/deposit.py
odoo/addons/delivery_roulier_geodis_fr/models/stock_picking.py
odoo/addons/delivery_roulier_geodis_fr/models/stock_quant_package.py
odoo/addons/delivery_roulier_geodis_fr/static/description/icon.png
odoo/addons/delivery_roulier_geodis_fr/static/src/img/icon.png
odoo/addons/delivery_roulier_geodis_fr/static/src/img/logo.jpg
odoo/addons/delivery_roulier_geodis_fr/tests/__init__.py
odoo/addons/delivery_roulier_geodis_fr/tests/test_geodis_labels.py
odoo/addons/delivery_roulier_geodis_fr/tests/cassettes/GeodisFrLabelCase.test_addresses.yaml
odoo/addons/delivery_roulier_geodis_fr/tests/cassettes/GeodisFrLabelCase.test_labels.yaml
odoo/addons/delivery_roulier_geodis_fr/views/carrier_account_views.xml
odoo/addons/delivery_roulier_geodis_fr/views/delivery_carrier_agency_views.xml
odoo_addon_delivery_roulier_geodis_fr-16.0.1.1.1.dist-info/METADATA
odoo_addon_delivery_roulier_geodis_fr-16.0.1.1.1.dist-info/WHEEL
odoo_addon_delivery_roulier_geodis_fr-16.0.1.1.1.dist-info/top_level.txt
odoo_addon_delivery_roulier_geodis_fr-16.0.1.1.1.dist-info/RECORD
