Metadata-Version: 2.1
Name: odoo-addon-delivery_roulier_geodis_fr
Version: 16.0.1.1.1
Summary: Generate Label for Geodis logistic
Home-page: https://github.com/OCA/delivery-carrier
Author: Akretion, Odoo Community Association (OCA)
Author-email: support@odoo-community.org
License: AGPL-3
Classifier: Programming Language :: Python
Classifier: Framework :: Odoo
Classifier: Framework :: Odoo :: 16.0
Classifier: License :: OSI Approved :: GNU Affero General Public License v3
Requires-Python: >=3.10
Requires-Dist: odoo-addon-delivery-carrier-agency<16.1dev,>=16.0dev
Requires-Dist: odoo-addon-delivery-carrier-deposit<16.1dev,>=16.0dev
Requires-Dist: odoo-addon-delivery-roulier<16.1dev,>=16.0dev
Requires-Dist: odoo-addon-delivery-roulier-option<16.1dev,>=16.0dev
Requires-Dist: odoo-addon-l10n-fr-siret<16.1dev,>=16.0dev
Requires-Dist: odoo-addon-partner-address-split<16.1dev,>=16.0dev
Requires-Dist: odoo<16.1dev,>=16.0a
